dataframely/__init__.py
dataframely/_base_schema.py
dataframely/_compat.py
dataframely/_deprecation.py
dataframely/_filter.py
dataframely/_match_to_schema.py
dataframely/_native.abi3.so
dataframely/_native.pyi
dataframely/_plugin.py
dataframely/_polars.py
dataframely/_pydantic.py
dataframely/_rule.py
dataframely/_serialization.py
dataframely/_storage/__init__.py
dataframely/_storage/_base.py
dataframely/_storage/_exc.py
dataframely/_storage/constants.py
dataframely/_storage/delta.py
dataframely/_storage/parquet.py
dataframely/_typing.py
dataframely/collection/__init__.py
dataframely/collection/_base.py
dataframely/collection/collection.py
dataframely/collection/filter_result.py
dataframely/columns/__init__.py
dataframely/columns/_base.py
dataframely/columns/_mixins.py
dataframely/columns/_registry.py
dataframely/columns/_utils.py
dataframely/columns/any.py
dataframely/columns/array.py
dataframely/columns/binary.py
dataframely/columns/bool.py
dataframely/columns/categorical.py
dataframely/columns/datetime.py
dataframely/columns/decimal.py
dataframely/columns/enum.py
dataframely/columns/float.py
dataframely/columns/integer.py
dataframely/columns/list.py
dataframely/columns/object.py
dataframely/columns/string.py
dataframely/columns/struct.py
dataframely/config.py
dataframely/exc.py
dataframely/filter_result.py
dataframely/functional.py
dataframely/py.typed
dataframely/random.py
dataframely/schema.py
dataframely/testing/__init__.py
dataframely/testing/const.py
dataframely/testing/factory.py
dataframely/testing/mask.py
dataframely/testing/rules.py
dataframely/testing/storage.py
dataframely-2.6.0.dist-info/METADATA
dataframely-2.6.0.dist-info/WHEEL
dataframely-2.6.0.dist-info/licenses/LICENSE
dataframely-2.6.0.dist-info/RECORD
