Metadata-Version: 2.4
Name: dataframely
Version: 2.6.0
Classifier: Programming Language :: Python :: 3
Classifier: Programming Language :: Python :: 3.10
Classifier: Programming Language :: Python :: 3.11
Classifier: Programming Language :: Python :: 3.12
Classifier: Programming Language :: Python :: 3.13
Classifier: Programming Language :: Python :: 3.14
Requires-Dist: fsspec>=2025.9
Requires-Dist: numpy
Requires-Dist: polars>=1.35
Requires-Dist: typing-extensions ; python_full_version < '3.11'
Requires-Dist: deltalake ; extra == 'deltalake'
Requires-Dist: pyarrow ; extra == 'pyarrow'
Requires-Dist: pydantic>=2 ; extra == 'pydantic'
Requires-Dist: s3fs>=2025.9 ; extra == 's3'
Requires-Dist: sqlalchemy ; extra == 'sqlalchemy'
Provides-Extra: deltalake
Provides-Extra: pyarrow
Provides-Extra: pydantic
Provides-Extra: s3
Provides-Extra: sqlalchemy
License-File: LICENSE
Summary: A declarative, polars-native data frame validation library
Author-email: Andreas Albert <andreas.albert@quantco.com>, Daniel Elsner <daniel.elsner@quantco.com>, Oliver Borchert <oliver.borchert@quantco.com>
Requires-Python: >=3.10
Project-URL: Documentation, https://dataframely.readthedocs.io/
Project-URL: Repository, https://github.com/quantco/dataframely
